LICENSE
MANIFEST.in
setup.py
projnames/__init__.py
projnames/epsgnames.json
projnames.egg-info/PKG-INFO
projnames.egg-info/SOURCES.txt
projnames.egg-info/dependency_links.txt
projnames.egg-info/entry_points.txt
projnames.egg-info/top_level.txt