Metadata-Version: 2.1
Name: projnames
Version: 0.0.2
Summary: Projection name to/from epsg-code
Home-page: https://github.com/EMeraldGeo/projnames
Author: Egil Moeller
Author-email: em@emeraldgeo.no
License: UNKNOWN
Platform: UNKNOWN
